{
  "_class": "group",
  "booleanOperation": -1,
  "clippingMaskMode": 0,
  "do_objectID": "3CA157DA-E023-4F62-B7DD-F25A179B46EF",
  "frame": {
    "_class": "rect",
    "constrainProportions": false,
    "height": 48,
    "width": 328,
    "x": 16,
    "y": 1658
  },
  "groupLayout": {
    "_class": "MSImmutableFreeformGroupLayout"
  },
  "hasClickThrough": false,
  "hasClippingMask": false,
  "isFixedToViewport": false,
  "isFlippedHorizontal": false,
  "isFlippedVertical": false,
  "isLocked": false,
  "isVisible": true,
  "layerListExpandedType": 0,
  "layers": [
    {
      "class": "rectangle",
      "id": "30E4DC16-0DB9-4B7D-B7EB-A5E32EA005E4"
    },
    {
      "class": "symbolInstance",
      "id": "EC131BCA-54BE-46F9-A80C-AB1279963415"
    },
    {
      "class": "text",
      "id": "0C55E18E-46CF-4223-B5AF-8D94A4838ABF"
    }
  ],
  "name": "Frame/FAQ Entry",
  "nameIsFixed": true,
  "resizingConstraint": 63,
  "resizingType": 0,
  "rotation": 0,
  "shouldBreakMaskChain": false,
  "style": {
    "_class": "style",
    "endMarkerType": 0,
    "miterLimit": 10,
    "startMarkerType": 0,
    "windingRule": 1
  },
  "userInfo": {
    "com.animaapp.stc-sketch-plugin": {
      "kModelPropertiesKey": {
      }
    }
  }
}