{
  "_class": "shapePath",
  "booleanOperation": 0,
  "clippingMaskMode": 0,
  "do_objectID": "C2A41D6F-452C-41B8-A3D9-9F14E4E25AB3",
  "edited": true,
  "frame": {
    "_class": "rect",
    "constrainProportions": false,
    "do_objectID": "EB383DDD-23F2-4910-AEE7-CB13855B307B",
    "height": 6.015920497798035,
    "width": 1.183682485608911,
    "x": 4.734729942435649,
    "y": 0
  },
  "hasClippingMask": false,
  "isClosed": true,
  "isFixedToViewport": false,
  "isFlippedHorizontal": false,
  "isFlippedVertical": false,
  "isLocked": false,
  "isVisible": true,
  "layerListExpandedType": 0,
  "name": "Path",
  "nameIsFixed": false,
  "pointRadiusBehaviour": 1,
  "points": [
    {
      "_class": "curvePoint",
      "cornerRadius": 0,
      "curveFrom": "{0.60902696365767894, 0}",
      "curveMode": 4,
      "curveTo": "{0.82473622508792421, 0}",
      "hasCurveFrom": false,
      "hasCurveTo": true,
      "point": "{0.60902696365767894, 0}"
    },
    {
      "_class": "curvePoint",
      "cornerRadius": 0,
      "curveFrom": "{0.17467760844079686, 0}",
      "curveMode": 4,
      "curveTo": "{0.39038686987104376, 0}",
      "hasCurveFrom": true,
      "hasCurveTo": false,
      "point": "{0.39038686987104376, 0}"
    },
    {
      "_class": "curvePoint",
      "cornerRadius": 0,
      "curveFrom": "{0, 0.081860579283259557}",
      "curveMode": 4,
      "curveTo": "{0, 0.036696121747668259}",
      "hasCurveFrom": false,
      "hasCurveTo": true,
      "point": "{0, 0.081860579283259557}"
    },
    {
      "_class": "curvePoint",
      "cornerRadius": 0,
      "curveFrom": "{0, 0.9633038782523321}",
      "curveMode": 4,
      "curveTo": "{0, 0.91813942071674048}",
      "hasCurveFrom": true,
      "hasCurveTo": false,
      "point": "{0, 0.91813942071674048}"
    },
    {
      "_class": "curvePoint",
      "cornerRadius": 0,
      "curveFrom": "{0.39038686987104376, 1}",
      "curveMode": 4,
      "curveTo": "{0.17467760844079686, 1}",
      "hasCurveFrom": false,
      "hasCurveTo": true,
      "point": "{0.39038686987104376, 1}"
    },
    {
      "_class": "curvePoint",
      "cornerRadius": 0,
      "curveFrom": "{0.82473622508792588, 1}",
      "curveMode": 4,
      "curveTo": "{0.60902696365767894, 1}",
      "hasCurveFrom": true,
      "hasCurveTo": false,
      "point": "{0.60902696365767894, 1}"
    },
    {
      "_class": "curvePoint",
      "cornerRadius": 0,
      "curveFrom": "{1, 0.91813942071674048}",
      "curveMode": 4,
      "curveTo": "{1, 0.96330387825233177}",
      "hasCurveFrom": false,
      "hasCurveTo": true,
      "point": "{1, 0.91813942071674048}"
    },
    {
      "_class": "curvePoint",
      "cornerRadius": 0,
      "curveFrom": "{1, 0.036696121747667905}",
      "curveMode": 4,
      "curveTo": "{1, 0.081860579283259904}",
      "hasCurveFrom": true,
      "hasCurveTo": false,
      "point": "{1, 0.081860579283259904}"
    }
  ],
  "resizingConstraint": 63,
  "resizingType": 0,
  "rotation": 0,
  "shouldBreakMaskChain": false,
  "style": {
    "_class": "style",
    "do_objectID": "A3B4F2E0-F53B-4BC9-9489-E4B55D485004",
    "endMarkerType": 0,
    "fills": [
      {
        "_class": "fill",
        "color": {
          "_class": "color",
          "alpha": 1,
          "blue": 0,
          "green": 0,
          "red": 0
        },
        "fillType": 0,
        "isEnabled": true,
        "noiseIndex": 0,
        "noiseIntensity": 0,
        "patternFillType": 1,
        "patternTileScale": 1
      }
    ],
    "miterLimit": 10,
    "startMarkerType": 0,
    "windingRule": 1
  },
  "userInfo": {
    "com.animaapp.stc-sketch-plugin": {
      "kModelPropertiesKey": {
      }
    }
  }
}