{
  "_class": "text",
  "attributedString": {
    "_class": "attributedString",
    "attributes": [
      {
        "_class": "stringAttribute",
        "attributes": {
          "MSAttributedStringColorAttribute": {
            "_class": "color",
            "alpha": 1,
            "blue": 0.3215686274509804,
            "green": 0.3215686274509804,
            "red": 0.3215686274509804
          },
          "MSAttributedStringFontAttribute": {
            "_class": "fontDescriptor",
            "attributes": {
              "name": "ProximaNova-Bold",
              "size": 24
            }
          },
          "kerning": -0.6,
          "paragraphStyle": {
            "_class": "paragraphStyle",
            "alignment": 0,
            "allowsDefaultTighteningForTruncation": 0
          },
          "textStyleVerticalAlignmentKey": 0
        },
        "length": 21,
        "location": 0
      }
    ],
    "string": "Rp350.000 - Rp500.000"
  },
  "automaticallyDrawOnUnderlyingPath": false,
  "booleanOperation": -1,
  "clippingMaskMode": 0,
  "do_objectID": "0B5BCF35-31C4-4D0C-8676-8F4FD38E8B30",
  "dontSynchroniseWithSymbol": false,
  "frame": {
    "_class": "rect",
    "constrainProportions": false,
    "do_objectID": "75671260-08B0-425A-86C4-6A4A99A34C1A",
    "height": 29,
    "width": 254,
    "x": 0,
    "y": 17
  },
  "glyphBounds": "{{1, 7}, {253, 22}}",
  "hasClippingMask": false,
  "isFixedToViewport": false,
  "isFlippedHorizontal": false,
  "isFlippedVertical": false,
  "isLocked": false,
  "isVisible": true,
  "layerListExpandedType": 0,
  "lineSpacingBehaviour": 2,
  "name": "Rp350.000 - Rp500.00",
  "nameIsFixed": true,
  "resizingConstraint": 47,
  "resizingType": 0,
  "rotation": 0,
  "shouldBreakMaskChain": false,
  "style": {
    "_class": "style",
    "do_objectID": "013F538C-F38A-4A39-A1DD-4F016D2ABAF7",
    "endMarkerType": 0,
    "miterLimit": 10,
    "startMarkerType": 0,
    "textStyle": {
      "_class": "textStyle",
      "do_objectID": "764E461A-FC18-415E-9563-7812E8F48B99",
      "encodedAttributes": {
        "MSAttributedStringColorAttribute": {
          "_class": "color",
          "alpha": 1,
          "blue": 0.3215686274509804,
          "green": 0.3215686274509804,
          "red": 0.3215686274509804
        },
        "MSAttributedStringFontAttribute": {
          "_class": "fontDescriptor",
          "attributes": {
            "name": "ProximaNova-Bold",
            "size": 24
          }
        },
        "kerning": -0.6,
        "paragraphStyle": {
          "_class": "paragraphStyle",
          "alignment": 0,
          "allowsDefaultTighteningForTruncation": 0
        },
        "textStyleVerticalAlignmentKey": 0
      },
      "verticalAlignment": 0
    },
    "windingRule": 1
  },
  "textBehaviour": 0,
  "userInfo": {
    "com.animaapp.stc-sketch-plugin": {
      "kModelPropertiesKey": {
        "isAutoWidth": 1
      }
    }
  }
}