{
  "_class": "symbolInstance",
  "booleanOperation": -1,
  "clippingMaskMode": 0,
  "do_objectID": "588C4980-31FB-48C1-A8B8-B23CF82D659D",
  "frame": {
    "_class": "rect",
    "constrainProportions": false,
    "height": 44,
    "width": 328,
    "x": 18,
    "y": 574
  },
  "hasClippingMask": false,
  "horizontalSpacing": 0,
  "isFixedToViewport": false,
  "isFlippedHorizontal": false,
  "isFlippedVertical": false,
  "isLocked": false,
  "isVisible": true,
  "layerListExpandedType": 0,
  "name": "Atoms/Button/Secondary Button Copy",
  "nameIsFixed": false,
  "overrideValues": [
    {
      "_class": "overrideValue",
      "overrideName": "BD4168DD-8A6A-4611-843F-50365D40CF8E_stringValue",
      "value": "Lihat Penawaran Awal"
    }
  ],
  "resizingConstraint": 63,
  "resizingType": 0,
  "rotation": 0,
  "scale": 1,
  "shouldBreakMaskChain": false,
  "style": {
    "_class": "style",
    "endMarkerType": 0,
    "miterLimit": 10,
    "startMarkerType": 0,
    "windingRule": 1
  },
  "symbolID": "55738B71-9503-4ACD-82EC-8B2E1D665B92",
  "verticalSpacing": 0
}