{
  "_class": "group",
  "booleanOperation": -1,
  "clippingMaskMode": 0,
  "do_objectID": "BC6B1B30-D622-4794-BC85-9435742F6D8E",
  "exportOptions": {
    "_class": "exportOptions",
    "exportFormats": [
    ],
    "includedLayerIds": [
    ],
    "layerOptions": 0,
    "shouldTrim": false
  },
  "frame": {
    "_class": "rect",
    "constrainProportions": false,
    "do_objectID": "78136457-1808-482C-9FAE-3A4951929419",
    "height": 20,
    "width": 239,
    "x": 0,
    "y": 30
  },
  "groupLayout": {
    "_class": "MSImmutableFreeformGroupLayout",
    "do_objectID": "F93C50F2-9959-4ED4-BBEB-ABE74361DCF7"
  },
  "hasClickThrough": false,
  "hasClippingMask": false,
  "isFixedToViewport": false,
  "isFlippedHorizontal": false,
  "isFlippedVertical": false,
  "isLocked": false,
  "isVisible": true,
  "layerListExpandedType": 2,
  "layers": [
    {
      "class": "text",
      "id": "CB84C629-BF71-48D6-8B7F-6A8639591B24"
    }
  ],
  "name": "Group 4",
  "nameIsFixed": false,
  "resizingConstraint": 63,
  "resizingType": 0,
  "rotation": 0,
  "shouldBreakMaskChain": false,
  "style": {
    "_class": "style",
    "do_objectID": "FD64064F-B87B-4372-AA4F-BD07E3DB6E96",
    "endMarkerType": 0,
    "miterLimit": 10,
    "startMarkerType": 0,
    "windingRule": 1
  },
  "userInfo": {
    "com.animaapp.stc-sketch-plugin": {
      "kModelPropertiesKey": {
        "padding": {
          "bottom": 6,
          "left": 10,
          "modelID": "viewPadding_6ad623a3-f767-4652-98d1-2ab69d6f1cd4",
          "model_class": "ADModelViewPadding",
          "model_version": 0.1,
          "right": 10,
          "top": 6
        },
        "stashedSizeH": [
          {
            "constant": 0,
            "enabled": 0,
            "modelID": "constraint_38962813-f47c-472f-88a3-6da5c1cc8c6e",
            "model_class": "ADModelConstraint",
            "model_version": 0.1,
            "multiplier": 0
          },
          {
            "constant": 0,
            "enabled": 0,
            "modelID": "constraint_295e7666-9584-4e90-8caa-e7dd97fa519d",
            "model_class": "ADModelConstraint",
            "model_version": 0.1,
            "multiplier": 0
          }
        ]
      }
    }
  }
}