{
  "_class": "group",
  "booleanOperation": -1,
  "clippingMaskMode": 0,
  "do_objectID": "0B38D8FF-C994-497B-B4EE-F2F105CAB040",
  "frame": {
    "_class": "rect",
    "constrainProportions": false,
    "height": 39,
    "width": 328,
    "x": 0,
    "y": 118
  },
  "groupLayout": {
    "_class": "MSImmutableFreeformGroupLayout"
  },
  "hasClickThrough": false,
  "hasClippingMask": false,
  "isFixedToViewport": false,
  "isFlippedHorizontal": false,
  "isFlippedVertical": false,
  "isLocked": false,
  "isVisible": true,
  "layerListExpandedType": 0,
  "layers": [
    {
      "class": "symbolInstance",
      "id": "643A1879-C8CE-4907-894E-4A92A1E099F3"
    },
    {
      "class": "symbolInstance",
      "id": "38D7C9DC-FEBF-4125-B9B3-D6F4C1D17DFA"
    }
  ],
  "name": "Group 7",
  "nameIsFixed": false,
  "resizingConstraint": 63,
  "resizingType": 0,
  "rotation": 0,
  "shouldBreakMaskChain": false,
  "style": {
    "_class": "style",
    "endMarkerType": 0,
    "miterLimit": 10,
    "startMarkerType": 0,
    "windingRule": 1
  },
  "userInfo": {
    "com.animaapp.stc-sketch-plugin": {
      "kModelPropertiesKey": {
        "align": 0,
        "constraints": {
          "automatic": 1,
          "modelID": "viewConstraints_db3ef7bd-4f51-4070-99b4-e74c1a688778",
          "model_class": "ADModelViewConstraints",
          "model_version": 0.1,
          "scaleFactor": 1,
          "width": {
            "constant": 328,
            "enabled": 1,
            "modelID": "constraint_52311834-b7bf-44c1-b991-93eff3d0b666",
            "model_class": "ADModelConstraint",
            "model_version": 0.1,
            "multiplier": 0
          }
        },
        "isCollapsing": 1,
        "resizesContainer": 1,
        "spacing": 8,
        "stackType": 1
      },
      "kViewTypeKey": "ADModelStackView"
    }
  }
}