{
  "_class": "symbolInstance",
  "booleanOperation": -1,
  "clippingMaskMode": 0,
  "do_objectID": "D426D098-FF05-45D5-A338-1DBA02FA2847",
  "exportOptions": {
    "_class": "exportOptions",
    "exportFormats": [
    ],
    "includedLayerIds": [
    ],
    "layerOptions": 0,
    "shouldTrim": false
  },
  "frame": {
    "_class": "rect",
    "constrainProportions": false,
    "do_objectID": "09374545-6B15-4834-9583-E9A8300A2CDF",
    "height": 28,
    "width": 227,
    "x": 31,
    "y": 188
  },
  "hasClippingMask": false,
  "horizontalSpacing": 0,
  "isFixedToViewport": false,
  "isFlippedHorizontal": false,
  "isFlippedVertical": false,
  "isLocked": false,
  "isVisible": true,
  "layerListExpandedType": 0,
  "name": "Atoms/Switch/Left",
  "nameIsFixed": false,
  "overrideValues": [
    {
      "_class": "overrideValue",
      "overrideName": "926D8048-9202-47DB-99C3-341FDEEABAD1_stringValue",
      "value": "12 Bulan"
    },
    {
      "_class": "overrideValue",
      "overrideName": "573FCC32-DF9F-47B8-BD29-D3C77ACCCCCC_stringValue",
      "value": "24 Bulan"
    }
  ],
  "resizingConstraint": 63,
  "resizingType": 0,
  "rotation": 0,
  "scale": 1,
  "shouldBreakMaskChain": false,
  "style": {
    "_class": "style",
    "do_objectID": "1847DBEE-3962-4C7E-B3EE-1FF8F76B4586",
    "endMarkerType": 0,
    "miterLimit": 10,
    "startMarkerType": 0,
    "windingRule": 1
  },
  "symbolID": "4485220A-526D-4C0A-B9DC-30FA84099DBD",
  "verticalSpacing": 0
}