{
  "_class": "symbolInstance",
  "booleanOperation": -1,
  "clippingMaskMode": 0,
  "do_objectID": "9446B55A-AC47-4801-BD97-1D795DDEE02C",
  "exportOptions": {
    "_class": "exportOptions",
    "exportFormats": [
    ],
    "includedLayerIds": [
    ],
    "layerOptions": 0,
    "shouldTrim": false
  },
  "frame": {
    "_class": "rect",
    "constrainProportions": false,
    "do_objectID": "333FB984-54F2-41C5-AD73-897FB25F631F",
    "height": 44,
    "width": 270,
    "x": 811,
    "y": 145
  },
  "hasClippingMask": false,
  "horizontalSpacing": 0,
  "isFixedToViewport": false,
  "isFlippedHorizontal": false,
  "isFlippedVertical": false,
  "isLocked": false,
  "isVisible": true,
  "layerListExpandedType": 0,
  "name": "Atoms/Button/Primary Button",
  "nameIsFixed": false,
  "overrideValues": [
    {
      "_class": "overrideValue",
      "do_objectID": "2EED394B-66AA-4544-B4C1-EAE5240AD67C",
      "overrideName": "3BC6FDC3-5426-4F11-ACE4-CF2B7AE455C8_stringValue",
      "value": "Ajukan Sekarang"
    }
  ],
  "resizingConstraint": 63,
  "resizingType": 0,
  "rotation": 0,
  "scale": 1,
  "shouldBreakMaskChain": false,
  "style": {
    "_class": "style",
    "do_objectID": "56789B36-A625-4500-B62F-E27FD9A244E9",
    "endMarkerType": 0,
    "miterLimit": 10,
    "startMarkerType": 0,
    "windingRule": 1
  },
  "symbolID": "61FB1D91-3AE8-4732-B121-3E97803B3394",
  "verticalSpacing": 0
}