{
  "_class": "group",
  "booleanOperation": -1,
  "clippingMaskMode": 0,
  "do_objectID": "3639EC18-F50E-4B11-9EAC-699C35BC2477",
  "frame": {
    "_class": "rect",
    "constrainProportions": false,
    "height": 56,
    "width": 360,
    "x": 0,
    "y": 0
  },
  "groupLayout": {
    "_class": "MSImmutableFreeformGroupLayout"
  },
  "hasClickThrough": false,
  "hasClippingMask": false,
  "isFixedToViewport": false,
  "isFlippedHorizontal": false,
  "isFlippedVertical": false,
  "isLocked": false,
  "isVisible": true,
  "layerListExpandedType": 2,
  "layers": [
    {
      "class": "rectangle",
      "id": "E324FB97-23E4-456A-8458-1A2D31527741"
    },
    {
      "class": "group",
      "id": "27B5D8CF-A5AB-4A23-8B60-9FDF29C9A9A7"
    },
    {
      "class": "symbolInstance",
      "id": "17ED90F8-AEF6-40C2-8FE8-DFD808501073"
    }
  ],
  "name": "Group",
  "nameIsFixed": false,
  "resizingConstraint": 45,
  "resizingType": 0,
  "rotation": 0,
  "shouldBreakMaskChain": false,
  "style": {
    "_class": "style",
    "endMarkerType": 0,
    "miterLimit": 10,
    "startMarkerType": 0,
    "windingRule": 1
  }
}