{
  "_class": "group",
  "booleanOperation": -1,
  "clippingMaskMode": 0,
  "do_objectID": "C78EF4EA-1C73-4C9E-834A-E17CAA461AC0",
  "frame": {
    "_class": "rect",
    "constrainProportions": false,
    "height": 2,
    "width": 210,
    "x": 75,
    "y": 42
  },
  "groupLayout": {
    "_class": "MSImmutableFreeformGroupLayout"
  },
  "hasClickThrough": false,
  "hasClippingMask": false,
  "isFixedToViewport": false,
  "isFlippedHorizontal": false,
  "isFlippedVertical": false,
  "isLocked": false,
  "isVisible": true,
  "layerListExpandedType": 1,
  "layers": [
    {
      "class": "rectangle",
      "id": "B1DBEBDD-A960-485F-B948-FAF9794DDCE5"
    },
    {
      "class": "rectangle",
      "id": "4D97141A-C004-4DA4-9E48-5FD2CFE42420"
    },
    {
      "class": "rectangle",
      "id": "C60A057D-629B-4F82-8E57-37A7BC6333E8"
    }
  ],
  "name": "Line",
  "nameIsFixed": true,
  "resizingConstraint": 47,
  "resizingType": 0,
  "rotation": 0,
  "shouldBreakMaskChain": false,
  "style": {
    "_class": "style",
    "endMarkerType": 0,
    "miterLimit": 10,
    "startMarkerType": 0,
    "windingRule": 1
  },
  "userInfo": {
    "com.animaapp.stc-sketch-plugin": {
      "kModelPropertiesKey": {
        "align": 0,
        "constraints": {
          "automatic": 1,
          "centerHorizontally": {
            "constant": 0,
            "enabled": 1,
            "modelID": "constraint_f607ec29-9476-4fae-af40-b4d52a70d865",
            "model_class": "ADModelConstraint",
            "model_version": 0,
            "multiplier": 0
          },
          "modelID": "viewConstraints_4b12cece-792e-466b-98d0-6665737e1bbd",
          "model_class": "ADModelViewConstraints",
          "model_version": 0,
          "scaleFactor": 1,
          "top": {
            "constant": 42,
            "enabled": 1,
            "modelID": "constraint_6ad83280-c0bd-46f8-82ad-f21aba7fd37e",
            "model_class": "ADModelConstraint",
            "model_version": 0,
            "multiplier": 0
          },
          "width": {
            "constant": 210,
            "enabled": 1,
            "modelID": "constraint_d9b3f510-1708-4768-83c1-2c3a0ebeddbf",
            "model_class": "ADModelConstraint",
            "model_version": 0,
            "multiplier": 0
          }
        },
        "isCollapsing": 1,
        "resizesContainer": 1,
        "spacing": 42,
        "stackType": 1
      },
      "kViewTypeKey": "ADModelStackView"
    }
  }
}