{
  "_class": "sharedStyle",
  "do_objectID": "8FBC159A-3B67-4B60-8228-1561E0855A44",
  "name": "Heading 1/Right/SemiBold/Grey6",
  "value": {
    "_class": "style",
    "endMarkerType": 0,
    "miterLimit": 10,
    "startMarkerType": 0,
    "textStyle": {
      "_class": "textStyle",
      "encodedAttributes": {
        "MSAttributedStringColorAttribute": {
          "_class": "color",
          "alpha": 1,
          "blue": 0.3215686274509804,
          "green": 0.3215686274509804,
          "red": 0.3215686274509804
        },
        "MSAttributedStringFontAttribute": {
          "_class": "fontDescriptor",
          "attributes": {
            "name": "ProximaNova-Semibold",
            "size": 48
          }
        },
        "kerning": -1.2,
        "paragraphStyle": {
          "_class": "paragraphStyle",
          "alignment": 1,
          "allowsDefaultTighteningForTruncation": 0
        },
        "textStyleVerticalAlignmentKey": 0
      },
      "verticalAlignment": 1
    },
    "windingRule": 1
  }
}